service_configuration_controller/__init__.py
service_configuration_controller/request_service_configuration.py
service_configuration_controller/communication/__init__.py
service_configuration_controller/communication/consumers.py
service_configuration_controller/helpers/__init__.py
service_configuration_controller/helpers/confluent_kafka_configuration_builder.py
service_configuration_controller/helpers/decode_messages.py
service_configuration_controller/helpers/operation_with_files.py
service_configuration_controller/std_ssl_cert/__init__.py
service_configuration_controller/tests/__init__.py
service_configuration_controller/tests/test_decode_data.py
service_configuration_controller/tests/test_write_data.py
service_configuration_layer-0.0.7.dist-info/METADATA
service_configuration_layer-0.0.7.dist-info/WHEEL
service_configuration_layer-0.0.7.dist-info/top_level.txt
service_configuration_layer-0.0.7.dist-info/RECORD
