Metadata-Version: 2.1
Name: service-configuration-layer
Version: 0.0.7
Summary: A tool to request and store services configuration. This tool is part of the Microservices ToolBox
Home-page: https://github.com/antoniodimariano/services_configuration_tool
Author: Antonio Di Mariano
Author-email: antonio.dimariano@gmail.com
License: UNKNOWN
Platform: UNKNOWN
Classifier: Programming Language :: Python :: 3
Classifier: License :: OSI Approved :: MIT License
Classifier: Operating System :: OS Independent
Requires-Python: ~=3.7
Requires-Dist: avro-python3
Requires-Dist: requests
Requires-Dist: confluent-kafka
Requires-Dist: confluent-kafka-producers-wrapper
